malphite/__init__.py
malphite/camera.py
malphite/data_server.py
malphite/py.typed
malphite/shared_memory.py
malphite-0.1.3.dist-info/METADATA
malphite-0.1.3.dist-info/WHEEL
malphite-0.1.3.dist-info/licenses/LICENSE
malphite-0.1.3.dist-info/RECORD
