Metadata-Version: 2.4
Name: malphite
Version: 0.1.3
Summary: Shared Camera Library for Python.
Project-URL: Repository, https://github.com/Bardreamaster/malphite
Author-email: WeiJinqi <changshanshi@outlook.com>
License: MIT License
License-File: LICENSE
Keywords: camera,opencv,python,shared,shared memory
Classifier: Development Status :: 3 - Alpha
Classifier: Intended Audience :: Developers
Classifier: Programming Language :: Python :: 3
Requires-Python: >=3.10
Requires-Dist: opencv-python>=4.11.0.86
Requires-Dist: sharklog>=0.1.1
Provides-Extra: dev
Requires-Dist: black; extra == 'dev'
Requires-Dist: pre-commit; extra == 'dev'
Requires-Dist: pytest; extra == 'dev'
Requires-Dist: ruff; extra == 'dev'
